odoo9_addon_website_snippet_marginless_gallery-9.0.1.0.0-py2.7-nspkg.pth
odoo9_addon_website_snippet_marginless_gallery-9.0.1.0.0.dist-info/DESCRIPTION.rst
odoo9_addon_website_snippet_marginless_gallery-9.0.1.0.0.dist-info/METADATA
odoo9_addon_website_snippet_marginless_gallery-9.0.1.0.0.dist-info/RECORD
odoo9_addon_website_snippet_marginless_gallery-9.0.1.0.0.dist-info/WHEEL
odoo9_addon_website_snippet_marginless_gallery-9.0.1.0.0.dist-info/metadata.json
odoo9_addon_website_snippet_marginless_gallery-9.0.1.0.0.dist-info/namespace_packages.txt
odoo9_addon_website_snippet_marginless_gallery-9.0.1.0.0.dist-info/top_level.txt
odoo_addons/website_snippet_marginless_gallery/README.rst
odoo_addons/website_snippet_marginless_gallery/__init__.py
odoo_addons/website_snippet_marginless_gallery/__openerp__.py
odoo_addons/website_snippet_marginless_gallery/demo/assets.xml
odoo_addons/website_snippet_marginless_gallery/i18n/de.po
odoo_addons/website_snippet_marginless_gallery/i18n/es.po
odoo_addons/website_snippet_marginless_gallery/i18n/it.po
odoo_addons/website_snippet_marginless_gallery/i18n/pt_BR.po
odoo_addons/website_snippet_marginless_gallery/i18n/ru.po
odoo_addons/website_snippet_marginless_gallery/i18n/sl.po
odoo_addons/website_snippet_marginless_gallery/images/marginless_gallery.png
odoo_addons/website_snippet_marginless_gallery/static/description/icon.png
odoo_addons/website_snippet_marginless_gallery/static/description/icon.svg
odoo_addons/website_snippet_marginless_gallery/static/src/css/website_snippet_marginless_gallery.sass
odoo_addons/website_snippet_marginless_gallery/static/src/js/website_snippet_marginless_gallery.editor.js
odoo_addons/website_snippet_marginless_gallery/static/src/js/website_snippet_marginless_gallery.tour.js
odoo_addons/website_snippet_marginless_gallery/tests/__init__.py
odoo_addons/website_snippet_marginless_gallery/tests/test_ui.py
odoo_addons/website_snippet_marginless_gallery/views/assets.xml
odoo_addons/website_snippet_marginless_gallery/views/snippets.xml
